Metadata-Version: 2.1
Name: mos
Version: 0.1.0
Summary: Media Open Souce, package is coming soon!
Home-page: https://github.com/sjtu-media/mos
Author: sjtu media team
Author-email: me@example.com
License: MIT
Platform: UNKNOWN
Classifier: License :: OSI Approved :: MIT License
Classifier: Programming Language :: Python
Classifier: Programming Language :: Python :: 3
Classifier: Programming Language :: Python :: 3.6
Classifier: Programming Language :: Python :: Implementation :: CPython
Classifier: Programming Language :: Python :: Implementation :: PyPy
Requires-Python: >=3.6.0
